test/calculator.py
simpleCalculatorPlan11-0.0.1.dist-info/METADATA
simpleCalculatorPlan11-0.0.1.dist-info/WHEEL
simpleCalculatorPlan11-0.0.1.dist-info/top_level.txt
simpleCalculatorPlan11-0.0.1.dist-info/RECORD
