Metadata-Version: 2.1
Name: simpleCalculatorPlan11
Version: 0.0.1
Summary: simple calculator
Home-page: https://github.com/plan11plan/simple
Download-URL: https://github.com/plan11plan/simple
Author: jins
Classifier: Programming Language :: Python :: 3
